pknsetools-0.1.20260108.149.data/purelib/PKNSETools/PKAllStocks.py
pknsetools-0.1.20260108.149.data/purelib/PKNSETools/PKCompanyGeneral.py
pknsetools-0.1.20260108.149.data/purelib/PKNSETools/PKCompanyStock.py
pknsetools-0.1.20260108.149.data/purelib/PKNSETools/PKConstants.py
pknsetools-0.1.20260108.149.data/purelib/PKNSETools/PKIntraDay.py
pknsetools-0.1.20260108.149.data/purelib/PKNSETools/PKNSEStockDataFetcher.py
pknsetools-0.1.20260108.149.data/purelib/PKNSETools/README.txt
pknsetools-0.1.20260108.149.data/purelib/PKNSETools/__init__.py
pknsetools-0.1.20260108.149.data/purelib/PKNSETools/requirements.txt
pknsetools-0.1.20260108.149.data/purelib/PKNSETools/Benny/NSE.py
pknsetools-0.1.20260108.149.data/purelib/PKNSETools/Benny/__init__.py
pknsetools-0.1.20260108.149.data/purelib/PKNSETools/Nasdaq/PKNasdaqIndex.py
pknsetools-0.1.20260108.149.data/purelib/PKNSETools/Nasdaq/__init__.py
pknsetools-0.1.20260108.149.data/purelib/PKNSETools/morningstartools/NSEStockDB.py
pknsetools-0.1.20260108.149.data/purelib/PKNSETools/morningstartools/NSEStockFairValueDB.py
pknsetools-0.1.20260108.149.data/purelib/PKNSETools/morningstartools/NSEStockMFIDB.py
pknsetools-0.1.20260108.149.data/purelib/PKNSETools/morningstartools/PKMorningstarDataFetcher.py
pknsetools-0.1.20260108.149.data/purelib/PKNSETools/morningstartools/__init__.py
pknsetools-0.1.20260108.149.data/purelib/PKNSETools/morningstartools/error.py
pknsetools-0.1.20260108.149.data/purelib/PKNSETools/morningstartools/funds.py
pknsetools-0.1.20260108.149.data/purelib/PKNSETools/morningstartools/search.py
pknsetools-0.1.20260108.149.data/purelib/PKNSETools/morningstartools/security.py
pknsetools-0.1.20260108.149.data/purelib/PKNSETools/morningstartools/stock.py
pknsetools-0.1.20260108.149.data/purelib/PKNSETools/morningstartools/utils.py
pknsetools-0.1.20260108.149.dist-info/METADATA
pknsetools-0.1.20260108.149.dist-info/WHEEL
pknsetools-0.1.20260108.149.dist-info/top_level.txt
pknsetools-0.1.20260108.149.dist-info/RECORD
