Metadata-Version: 2.4
Name: pknsetools
Version: 0.1.20260108.149
Summary: A Python-based data downloader for NSE, India
Home-page: https://github.com/pkjmesra/PKNSETools
Download-URL: https://github.com/pkjmesra/PKNSETools/archive/v0.1.20260108.149.zip
Author: pkjmesra
Author-email: pkjmesra@gmail.com
License: OSI Approved (MIT)
Keywords: NSE,Stocks,Data Download
Classifier: License :: OSI Approved :: MIT License
Classifier: Operating System :: Microsoft :: Windows
Classifier: Operating System :: MacOS
Classifier: Operating System :: POSIX :: Linux
Classifier: Programming Language :: Python
Classifier: Programming Language :: Python :: 3
Classifier: Programming Language :: Python :: 3.11
Classifier: Programming Language :: Python :: 3.12
Requires-Dist: brotli
Requires-Dist: bs4
Requires-Dist: mthrottle
Requires-Dist: numpy
Requires-Dist: pandas
Requires-Dist: PKDevTools>=0.13.20260108.322
Requires-Dist: pytz
Requires-Dist: requests
Requires-Dist: urllib3
Requires-Dist: xmltodict
Requires-Dist: yfinance
Dynamic: author
Dynamic: author-email
Dynamic: classifier
Dynamic: description
Dynamic: description-content-type
Dynamic: download-url
Dynamic: home-page
Dynamic: keywords
Dynamic: license
Dynamic: requires-dist
Dynamic: summary
